{
  "$schema": "https://developer.microsoft.com/json-schemas/fabric/item/report/definition/visualContainer/2.5.0/schema.json",
  "name": "5b10f0afccbbce004e6a",
  "position": {
    "x": 23.207981580966997,
    "y": 12.156561780506523,
    "z": 2000,
    "height": 60.782808902532615,
    "width": 158.03530314658479,
    "tabOrder": 2000
  },
  "visual": {
    "visualType": "image",
    "objects": {
      "general": [
        {
          "properties": {
            "imageUrl": {
              "expr": {
                "ResourcePackageItem": {
                  "PackageName": "RegisteredResources",
                  "PackageType": 1,
                  "ItemName": "tzumi_logo5035229447124863.png"
                }
              }
            }
          }
        }
      ]
    },
    "visualContainerObjects": {
      "title": [
        {
          "properties": {
            "text": {
              "expr": {
                "Literal": {
                  "Value": "'[Image] Tzumi logo'"
                }
              }
            }
          }
        }
      ]
    },
    "drillFilterOtherVisuals": true
  },
  "parentGroupName": "ed80e5049a0705c37e80",
  "howCreated": "InsertVisualButton"
}