{
  "$schema": "https://developer.microsoft.com/json-schemas/fabric/item/report/definition/visualContainer/2.5.0/schema.json",
  "name": "8e4cc598e4ce045c50d0",
  "position": {
    "x": 0,
    "y": 0,
    "z": 1000,
    "height": 129.40658461700446,
    "width": 249.43213082477556,
    "tabOrder": 1000
  },
  "visual": {
    "visualType": "actionButton",
    "objects": {
      "icon": [
        {
          "properties": {
            "shapeType": {
              "expr": {
                "Literal": {
                  "Value": "'blank'"
                }
              }
            }
          },
          "selector": {
            "id": "default"
          }
        }
      ],
      "outline": [
        {
          "properties": {
            "show": {
              "expr": {
                "Literal": {
                  "Value": "false"
                }
              }
            }
          }
        }
      ]
    },
    "visualContainerObjects": {
      "visualLink": [
        {
          "properties": {
            "show": {
              "expr": {
                "Literal": {
                  "Value": "true"
                }
              }
            },
            "tooltip": {
              "expr": {
                "Literal": {
                  "Value": "'# of POs with a cost per item < $1.'"
                }
              }
            },
            "type": {
              "expr": {
                "Literal": {
                  "Value": "'Bookmark'"
                }
              }
            },
            "bookmark": {
              "expr": {
                "Literal": {
                  "Value": "'3bf8264eaaa1e147ddfc'"
                }
              }
            },
            "navigationSection": {
              "expr": {
                "Literal": {
                  "Value": "'40e5f991da5d66dc30b0'"
                }
              }
            }
          }
        }
      ],
      "background": [
        {
          "properties": {
            "show": {
              "expr": {
                "Literal": {
                  "Value": "false"
                }
              }
            }
          }
        }
      ],
      "title": [
        {
          "properties": {
            "text": {
              "expr": {
                "Literal": {
                  "Value": "'Button - POs INACCURATE COSTING'"
                }
              }
            }
          }
        }
      ]
    },
    "drillFilterOtherVisuals": true
  },
  "parentGroupName": "3429c2b12edae338f203",
  "howCreated": "InsertVisualButton"
}