{
  "$schema": "https://developer.microsoft.com/json-schemas/fabric/item/report/definition/visualContainer/2.5.0/schema.json",
  "name": "efcbd02c851a2e8c001e",
  "position": {
    "x": 0,
    "y": 0,
    "z": 0,
    "height": 150,
    "width": 150,
    "tabOrder": 0
  },
  "visual": {
    "visualType": "simpleImageEBC4593F96F1425FB3D84C5BF02B5075",
    "query": {
      "queryState": {
        "imageURL": {
          "projections": [
            {
              "field": {
                "Column": {
                  "Expression": {
                    "SourceRef": {
                      "Entity": "bvc_OrderItem"
                    }
                  },
                  "Property": "Image URL"
                }
              },
              "queryRef": "bvc_OrderItem.Image URL",
              "nativeQueryRef": "Image URL"
            }
          ]
        }
      }
    },
    "objects": {
      "imageSettings": [
        {
          "properties": {
            "imageAlignment": {
              "expr": {
                "Literal": {
                  "Value": "'mcenter'"
                }
              }
            }
          }
        }
      ]
    },
    "drillFilterOtherVisuals": true
  }
}