{
  "$schema": "https://developer.microsoft.com/json-schemas/fabric/item/report/definition/visualContainer/2.5.0/schema.json",
  "name": "46fc7b017a6fbd6f7c2a",
  "position": {
    "x": 203.27242231638417,
    "y": 167.5,
    "z": 2000,
    "height": 57.022158058284752,
    "width": 217.44732020155746,
    "tabOrder": 10000
  },
  "visual": {
    "visualType": "slicer",
    "query": {
      "queryState": {
        "Values": {
          "projections": [
            {
              "field": {
                "Column": {
                  "Expression": {
                    "SourceRef": {
                      "Entity": "BVC_ORDER"
                    }
                  },
                  "Property": "OrderSource - CompanyName"
                }
              },
              "queryRef": "BVC_ORDER.OrderSource - CompanyName",
              "nativeQueryRef": "OrderSource - CompanyName",
              "active": true
            }
          ]
        }
      }
    },
    "objects": {
      "data": [
        {
          "properties": {
            "mode": {
              "expr": {
                "Literal": {
                  "Value": "'Dropdown'"
                }
              }
            },
            "isInvertedSelectionMode": {
              "expr": {
                "Literal": {
                  "Value": "true"
                }
              }
            }
          }
        }
      ],
      "general": [
        {
          "properties": {
            "selfFilterEnabled": {
              "expr": {
                "Literal": {
                  "Value": "true"
                }
              }
            }
          }
        }
      ],
      "selection": [
        {
          "properties": {
            "selectAllCheckboxEnabled": {
              "expr": {
                "Literal": {
                  "Value": "true"
                }
              }
            },
            "singleSelect": {
              "expr": {
                "Literal": {
                  "Value": "false"
                }
              }
            }
          }
        }
      ],
      "header": [
        {
          "properties": {
            "textSize": {
              "expr": {
                "Literal": {
                  "Value": "10D"
                }
              }
            }
          }
        }
      ],
      "items": [
        {
          "properties": {
            "fontFamily": {
              "expr": {
                "Literal": {
                  "Value": "'wf_standard-font, helvetica, arial, sans-serif'"
                }
              }
            },
            "textSize": {
              "expr": {
                "Literal": {
                  "Value": "8D"
                }
              }
            }
          }
        }
      ]
    },
    "syncGroup": {
      "groupName": "Inventory Management OS",
      "fieldChanges": true,
      "filterChanges": true
    },
    "drillFilterOtherVisuals": true
  }
}